Metadata-Version: 2.1
Name: simple-socket-client
Version: 1.5
Summary: Simple TCP socket client
Home-page: https://github.com/webtoucher/simple-socket-client
Author: Alexey Kuznetsov
Author-email: mirakuru@webtoucher.ru
License: BSD-3-Clause
Classifier: Development Status :: 5 - Production/Stable
Classifier: Intended Audience :: Developers
Classifier: License :: OSI Approved :: BSD License
Classifier: Programming Language :: Python :: 3
Classifier: Operating System :: Microsoft :: Windows
Classifier: Operating System :: POSIX
Classifier: Operating System :: Unix
Classifier: Operating System :: MacOS
License-File: LICENSE.md
